autools/__init__.py
autools/core.py
autools_isee-0.1.0.dist-info/METADATA
autools_isee-0.1.0.dist-info/WHEEL
autools_isee-0.1.0.dist-info/entry_points.txt
autools_isee-0.1.0.dist-info/top_level.txt
autools_isee-0.1.0.dist-info/RECORD
