Metadata-Version: 2.2
Name: autools_isee
Version: 0.1.0
Summary: Advanced string manipulation utilities
Home-page: 
Author: ISEE
Author-email: your.email@example.com
Classifier: Programming Language :: Python :: 3
Classifier: License :: OSI Approved :: MIT License
Classifier: Operating System :: OS Independent
Requires-Python: >=3.9
Requires-Dist: requests>=2.32.3
Provides-Extra: dev
Requires-Dist: requests>=2.32.3; extra == "dev"
Dynamic: author
Dynamic: author-email
Dynamic: classifier
Dynamic: description-content-type
Dynamic: provides-extra
Dynamic: requires-dist
Dynamic: requires-python
Dynamic: summary
